publication.py
publication-0.0.2.dist-info/LICENSE
publication-0.0.2.dist-info/WHEEL
publication-0.0.2.dist-info/METADATA
publication-0.0.2.dist-info/RECORD
