Metadata-Version: 2.1
Name: publication
Version: 0.0.2
Summary: C{publication} helps you maintain public-api-friendly modules by preventing
Home-page: https://github.com/glyph/publication
License: UNKNOWN
Author: Glyph
Author-email: glyph@twistedmatrix.com
Classifier: License :: OSI Approved :: MIT License
Classifier: Programming Language :: Python :: 3
Classifier: Programming Language :: Python :: 2
